{
    "occurrenceType": "Conservation",
    "relationshipType": "conservation",
    "preferred_labels": "^Conservation",
    "occurrenceName": "^Conservation",
    "name": "^Conservation",
    "matchOn": [
        "idno"
    ],
    "attributes":{
        "ConservationDetails": "^Conservation",
        "ConservationDate": "^ConservationDate",
        "Conservator": "^ConservationBy",
        "preferred_labels": "^Conservation",
        "preferred_labels.name": "^Conservation",
        "name": "^Conservation"
    }
}
